{"elementosViaje":[{"precio":123,"cantDias":0,"puntuacion":[],"ciudad":"123","desayuno":true,"provincia":"123","pais":"123"},{"precio":456,"provinciaOrigen":"456","ciudadOrigen":"456","provinciaDestino":"456","paisOrigen":"456","paisDestino":"456","fechaVuelo":"2024-10-31","ciudadDestino":"456"},{"tipoAsistencia":"789789sxw","precio":123,"cantDias":0,"asistenciaMedica":"w","perdidaEquipaje":"wdce","vueloDemorado":"cwe","destino":"bolivia","medicamentos":"ad`"},{"precio":456,"provinciaOrigen":"456","ciudadOrigen":"456","provinciaDestino":"456","paisOrigen":"456","paisDestino":"456","fechaVuelo":"2024-10-31","ciudadDestino":"456"}]}